odoo8_addon_purchase_transport_document-8.0.0.1.0.99.dev29-py3.8-nspkg.pth
odoo_addons/purchase_transport_document/README.rst
odoo_addons/purchase_transport_document/__init__.py
odoo_addons/purchase_transport_document/__openerp__.py
odoo_addons/purchase_transport_document/data/transport_document.xml
odoo_addons/purchase_transport_document/i18n/am.po
odoo_addons/purchase_transport_document/i18n/ar.po
odoo_addons/purchase_transport_document/i18n/bg.po
odoo_addons/purchase_transport_document/i18n/bs.po
odoo_addons/purchase_transport_document/i18n/ca.po
odoo_addons/purchase_transport_document/i18n/ca_ES.po
odoo_addons/purchase_transport_document/i18n/cs.po
odoo_addons/purchase_transport_document/i18n/da.po
odoo_addons/purchase_transport_document/i18n/de.po
odoo_addons/purchase_transport_document/i18n/el_GR.po
odoo_addons/purchase_transport_document/i18n/en_GB.po
odoo_addons/purchase_transport_document/i18n/es.po
odoo_addons/purchase_transport_document/i18n/es_AR.po
odoo_addons/purchase_transport_document/i18n/es_CL.po
odoo_addons/purchase_transport_document/i18n/es_CO.po
odoo_addons/purchase_transport_document/i18n/es_CR.po
odoo_addons/purchase_transport_document/i18n/es_DO.po
odoo_addons/purchase_transport_document/i18n/es_EC.po
odoo_addons/purchase_transport_document/i18n/es_ES.po
odoo_addons/purchase_transport_document/i18n/es_MX.po
odoo_addons/purchase_transport_document/i18n/es_PE.po
odoo_addons/purchase_transport_document/i18n/es_PY.po
odoo_addons/purchase_transport_document/i18n/es_VE.po
odoo_addons/purchase_transport_document/i18n/et.po
odoo_addons/purchase_transport_document/i18n/eu.po
odoo_addons/purchase_transport_document/i18n/fa.po
odoo_addons/purchase_transport_document/i18n/fi.po
odoo_addons/purchase_transport_document/i18n/fr.po
odoo_addons/purchase_transport_document/i18n/fr_CA.po
odoo_addons/purchase_transport_document/i18n/fr_CH.po
odoo_addons/purchase_transport_document/i18n/fr_FR.po
odoo_addons/purchase_transport_document/i18n/gl.po
odoo8_addon_purchase_transport_document-8.0.0.1.0.99.dev29.dist-info/METADATA
odoo8_addon_purchase_transport_document-8.0.0.1.0.99.dev29.dist-info/WHEEL
odoo8_addon_purchase_transport_document-8.0.0.1.0.99.dev29.dist-info/namespace_packages.txt
odoo8_addon_purchase_transport_document-8.0.0.1.0.99.dev29.dist-info/top_level.txt
odoo8_addon_purchase_transport_document-8.0.0.1.0.99.dev29.dist-info/RECORD
